sagemaker_huggingface_inference_toolkit/__init__.py
sagemaker_huggingface_inference_toolkit/content_types.py
sagemaker_huggingface_inference_toolkit/decoder_encoder.py
sagemaker_huggingface_inference_toolkit/diffusers_utils.py
sagemaker_huggingface_inference_toolkit/handler_service.py
sagemaker_huggingface_inference_toolkit/mms_model_server.py
sagemaker_huggingface_inference_toolkit/optimum_utils.py
sagemaker_huggingface_inference_toolkit/serving.py
sagemaker_huggingface_inference_toolkit/transformers_utils.py
sagemaker_huggingface_inference_toolkit-2.6.0.dist-info/licenses/LICENSE
sagemaker_huggingface_inference_toolkit-2.6.0.dist-info/licenses/NOTICE
sagemaker_huggingface_inference_toolkit-2.6.0.dist-info/METADATA
sagemaker_huggingface_inference_toolkit-2.6.0.dist-info/WHEEL
sagemaker_huggingface_inference_toolkit-2.6.0.dist-info/entry_points.txt
sagemaker_huggingface_inference_toolkit-2.6.0.dist-info/top_level.txt
sagemaker_huggingface_inference_toolkit-2.6.0.dist-info/RECORD
