Metadata-Version: 2.4
Name: sagemaker-huggingface-inference-toolkit
Version: 2.6.0
Summary: Open source library for running inference workload with Hugging Face Deep Learning Containers on Amazon SageMaker.
Home-page: https://github.com/aws/sagemaker-huggingface-inference-toolkit
Author: HuggingFace and Amazon Web Services
License: Apache License 2.0
Keywords: NLP deep-learning transformer pytorch tensorflow BERT GPT GPT-2 AWS Amazon SageMaker Cloud
Classifier: Development Status :: 5 - Production/Stable
Classifier: Intended Audience :: Developers
Classifier: Intended Audience :: Education
Classifier: Intended Audience :: Science/Research
Classifier: License :: OSI Approved :: Apache Software License
Classifier: Operating System :: OS Independent
Classifier: Programming Language :: Python :: 3
Classifier: Programming Language :: Python :: 3.6
Classifier: Programming Language :: Python :: 3.7
Classifier: Topic :: Scientific/Engineering :: Artificial Intelligence
Requires-Python: >=3.6.0
License-File: LICENSE
License-File: NOTICE
Requires-Dist: sagemaker-inference>=1.8.0
Requires-Dist: huggingface_hub>=0.0.8
Requires-Dist: retrying
Requires-Dist: numpy
Requires-Dist: Pillow
Requires-Dist: librosa
Requires-Dist: pyctcdecode>=0.3.0
Requires-Dist: phonemizer
Provides-Extra: transformers
Requires-Dist: transformers[sentencepiece,sklearn]>=4.17.0; extra == "transformers"
Provides-Extra: diffusers
Requires-Dist: diffusers>=0.23.0; extra == "diffusers"
Provides-Extra: torch
Requires-Dist: torch>=1.8.0; extra == "torch"
Requires-Dist: torchaudio; extra == "torch"
Provides-Extra: tensorflow
Requires-Dist: tensorflow<2.11,>=2.4.0; extra == "tensorflow"
Provides-Extra: mms
Requires-Dist: multi-model-server>=1.1.4; extra == "mms"
Requires-Dist: retrying; extra == "mms"
Provides-Extra: test
Requires-Dist: pytest<8; extra == "test"
Requires-Dist: pytest-xdist; extra == "test"
Requires-Dist: parameterized; extra == "test"
Requires-Dist: psutil; extra == "test"
Requires-Dist: datasets; extra == "test"
Requires-Dist: pytest-sugar; extra == "test"
Requires-Dist: black==21.4b0; extra == "test"
Requires-Dist: sagemaker; extra == "test"
Requires-Dist: boto3; extra == "test"
Requires-Dist: mock==2.0.0; extra == "test"
Provides-Extra: benchmark
Requires-Dist: boto3; extra == "benchmark"
Requires-Dist: locust; extra == "benchmark"
Provides-Extra: quality
Requires-Dist: black>=21.10; extra == "quality"
Requires-Dist: isort>=5.5.4; extra == "quality"
Requires-Dist: flake8>=3.8.3; extra == "quality"
Provides-Extra: dev
Requires-Dist: transformers[sentencepiece,sklearn]>=4.17.0; extra == "dev"
Requires-Dist: multi-model-server>=1.1.4; extra == "dev"
Requires-Dist: retrying; extra == "dev"
Requires-Dist: torch>=1.8.0; extra == "dev"
Requires-Dist: torchaudio; extra == "dev"
Requires-Dist: tensorflow<2.11,>=2.4.0; extra == "dev"
Requires-Dist: diffusers>=0.23.0; extra == "dev"
Dynamic: author
Dynamic: classifier
Dynamic: description
Dynamic: description-content-type
Dynamic: home-page
Dynamic: keywords
Dynamic: license
Dynamic: license-file
Dynamic: provides-extra
Dynamic: requires-dist
Dynamic: requires-python
Dynamic: summary
